{"format_version":"1.19.80","minecraft:entity":{"description":{"identifier":"spark:delay_spawn","properties":{"spark:activated":{"type":"bool","default":false,"client_sync":false},"spark:type":{"type":"enum","default":"b1_battle_droid","values":["b1_battle_droid","b2_battle_droid"],"client_sync":false}},"animations":{"activate":"controller.animation.spark.delay_spawn.activate"},"scripts":{"animate":["activate"]},"is_summonable":true},"components":{"minecraft:physics":{"has_collision":true,"has_gravity":true,"push_towards_closest_space":false},"minecraft:pushable":{"is_pushable":false,"is_pushable_by_piston":false},"minecraft:knockback_resistance":{"value":1},"minecraft:collision_box":{"height":0,"width":0},"minecraft:damage_sensor":{"triggers":[{"cause":"all","deals_damage":false}]},"minecraft:timer":{"time":[0.3,10],"looping":false,"time_down_event":{"event":"spark:trigger","target":"self"}}},"component_groups":{"despawn":{"minecraft:instant_despawn":{}}},"events":{"spark:despawn":{"add":{"component_groups":["despawn"]}},"spark:trigger":{"set_property":{"spark:activated":true}},"spark:b1_battle_droid":{"set_property":{"spark:type":"b1_battle_droid"}},"spark:b2_battle_droid":{"set_property":{"spark:type":"b2_battle_droid"}}}}}
