{"format_version":"1.19.0","minecraft:client_entity":{"description":{"identifier":"spark:vision_darth_sidious","materials":{"default":"entity_glow_base","outline":"entity_glow_outline","blade":"entity_emissive","glow":"lightsaber_glow"},"textures":{"default":"textures/spark/entity/character/ancient_puzzle/vision_darth_sidious","glow":"textures/spark/entity/character/ancient_puzzle/vision_darth_sidious_glow"},"geometry":{"default":"geometry.spark.vision_darth_sidious","glow":"geometry.spark.vision_darth_sidious_glow"},"render_controllers":["controller.render.spark.sith_vision","controller.render.spark.sith_vision.lightsaber","controller.render.spark.sith_vision.glow"],"animations":{"look_at_target":"animation.humanoid.look_at_target.default","idle":"animation.spark.vision_darth_sidious.idle","walk":"animation.spark.vision_darth_sidious.walk","sit":"animation.spark.vision_darth_sidious.idle","movement":"controller.animation.spark.duel_opponent.movement","attack1":"animation.spark.vision_darth_sidious.attack1","attack2":"animation.spark.vision_darth_sidious.attack2","attack3":"animation.spark.vision_darth_sidious.attack3","guard":"animation.spark.vision_darth_sidious.guard","withdraw":"animation.spark.vision_darth_sidious.withdraw","power_attack":"animation.spark.vision_darth_sidious.power_attack","special_attack":"animation.spark.vision_darth_sidious.lightning_attack","dash_forward":"animation.spark.vision_darth_sidious.dash_forward","dash_left":"animation.spark.vision_darth_sidious.dash_left","dash_right":"animation.spark.vision_darth_sidious.dash_right","dash_backward":"animation.spark.vision_darth_sidious.dash_backwards","block":"animation.spark.vision_darth_sidious.block","block_react1":"animation.spark.vision_darth_sidious.block_react1","block_react2":"animation.spark.vision_darth_sidious.block_react2","defeated":"animation.spark.vision_darth_sidious.weak","appear":"animation.spark.vision_darth_maul.appear","disappear":"animation.spark.vision_darth_maul.disappear","dueling":"controller.animation.spark.sith_opponent.dueling","recoil1":"animation.spark.vision_darth_sidious.hit_react1","recoil2":"animation.spark.vision_darth_sidious.hit_react2","recoil3":"animation.spark.vision_darth_sidious.hit_react3","recoil_controller":"controller.animation.spark.character.recoil","blink":"animation.spark.character.blink","blink_state":"animation.spark.character.blink_state","lightsaber_sound_anim":"animation.spark.duel_opponent.lightsaber.sound","appear_sound_animation":"animation.spark.appear_sound"},"scripts":{"initialize":["v.last_health = q.health;","v.last_hurt = -100;","v.hurt_overlay = 0;","v.attack_variant = 0;","v.recoil_variant = 0;","v.block_react_variant = 0;","v.blinking = false;"],"pre_animation":["v.hurt_overlay = Math.clamp(1 - (q.life_time - v.last_hurt)/0.5, 0, 1);"],"should_update_effects_offscreen":true,"animate":["look_at_target","appear","appear_sound_animation",{"movement":"q.property('spark:move') == 'none'"},{"dueling":"q.property('spark:move') != 'none'"},{"lightsaber_sound_anim":"q.property('spark:move') != 'none'"},"recoil_controller","blink","blink_state"]},"particle_effects":{"lightning_attack":"spark:lightning_attack","appear":"spark:vision_appear","disappear":"spark:vision_disappear"},"sound_effects":{"lightsaber_loop_sound":"sound.spark.sith_lightsaber_loop","power_sound":"sound.spark.palpatine_power","special_sound":"sound.spark.palpatine_special","ignite_sound":"sound.spark.sith_lightsaber_draw","sheathe_sound":"sound.spark.sith_lightsaber_sheathe","appear_sound":"sound.spark.vision_appear","disappear_sound":"sound.spark.vision_disappear"}}}}
