{"format_version":"1.12.0","minecraft:geometry":[{"description":{"identifier":"geometry.spark.kamino_antenna_small","texture_width":64,"texture_height":64,"visible_bounds_width":3,"visible_bounds_height":6,"visible_bounds_offset":[0,2,0]},"bones":[{"name":"base","pivot":[0,6,0],"cubes":[{"origin":[-4,0,-4],"size":[8,16,8],"uv":[0,0]}]},{"name":"middle","pivot":[0,24,0],"cubes":[{"origin":[-4,16,-4],"size":[8,2,8],"uv":[32,12]},{"origin":[-3,18,-3],"size":[6,14,6],"uv":[0,24]}]},{"name":"top","pivot":[0,39,0],"cubes":[{"origin":[-3,32,-3],"size":[6,8,6],"uv":[24,24]},{"origin":[-1,40,-1],"size":[2,8,2],"uv":[32,38]}]},{"name":"tip","pivot":[0,57,0],"cubes":[{"origin":[-1,48,-1],"size":[2,16,2],"uv":[24,38]}]}]}]}
