{"format_version":"1.19.0","minecraft:client_entity":{"description":{"identifier":"spark:general_grievous","materials":{"default":"entity_alphatest","blade":"entity_emissive","glow":"lightsaber_glow"},"textures":{"default":"textures/spark/entity/character/escape_battleship/general_grievous"},"geometry":{"default":"geometry.spark.general_grievous"},"render_controllers":["controller.render.spark.character_w_lightsaber"],"animations":{"look_at_target":"animation.common.look_at_target","idle_upperbody":"animation.spark.general_grievous.idle_upperbody","idle_lowerbody":"animation.spark.general_grievous.idle_lowerbody","guard_upperbody":"animation.spark.general_grievous.guard_upperbody","guard_lowerbody":"animation.spark.general_grievous.guard_lowerbody","walk_upperbody":"animation.spark.general_grievous.walk_upperbody","walk_lowerbody":"animation.spark.general_grievous.walk_lowerbody","walk2_upperbody":"animation.spark.general_grievous.walk2_upperbody","walk2_lowerbody":"animation.spark.general_grievous.walk2_lowerbody","dash_forward_upperbody":"animation.spark.general_grievous.dash_forward_upperbody","dash_forward_lowerbody":"animation.spark.general_grievous.dash_forward_lowerbody","lawn_mower_upperbody":"animation.spark.general_grievous.lawn_mower_upperbody","lawn_mower_lowerbody":"animation.spark.general_grievous.lawn_mower_lowerbody","dash_backward_upperbody":"animation.spark.general_grievous.dash_backward_upperbody","dash_backward_lowerbody":"animation.spark.general_grievous.dash_backward_lowerbody","attack1":"animation.spark.general_grievous.attack1","attack2":"animation.spark.general_grievous.attack2","attack3":"animation.spark.general_grievous.attack3","parry1":"animation.spark.general_grievous.parry1","parry2":"animation.spark.general_grievous.parry2","lower_controller":"controller.animation.spark.general_grievous.lower","upper_controller":"controller.animation.spark.general_grievous.upper","parry_controller":"controller.animation.spark.general_grievous.parry","recoil1":"animation.spark.general_grievous.hit_react1","recoil2":"animation.spark.general_grievous.hit_react2","recoil3":"animation.spark.general_grievous.hit_react3","recoil_controller":"controller.animation.spark.character.recoil"},"scripts":{"initialize":["v.last_health = q.health;","v.last_hurt = -100;","v.hurt_overlay = 0;","v.attack_variant = 0;","v.recoil_variant = 0;","v.block_react_variant = 0;"],"pre_animation":["v.hurt_overlay = Math.clamp(1 - (q.life_time - v.last_hurt)/0.3, 0, 1);"],"animate":["look_at_target","lower_controller","upper_controller","parry_controller","recoil_controller"]},"particle_effects":{"ground_marks":"spark:grievous_ground_marks","ground_sparks":"spark:grievous_ground_sparks"},"sound_effects":{"disengage_sound":"sound.spark.duelist_disengage","move_sound":"sound.spark.grievous_move","step_sound":"sound.spark.misc.mute"}}}}
