{"format_version":"1.12.0","minecraft:geometry":[{"description":{"identifier":"geometry.spark.dojo_banner","texture_width":128,"texture_height":128,"visible_bounds_width":12,"visible_bounds_height":6,"visible_bounds_offset":[0,2,0]},"bones":[{"name":"root","pivot":[0,0,0],"cubes":[{"origin":[-22,64,7],"size":[44,8,0],"uv":{"north":{"uv":[0,68],"uv_size":[44,8]}}}]},{"name":"dojo_banner","parent":"root","pivot":[0,64,7],"cubes":[{"origin":[-24,62,6],"size":[48,2,2],"uv":[0,63]},{"origin":[-22,0,7],"size":[44,62,0],"uv":{"north":{"uv":[0,0],"uv_size":[44,62]}}}]}]}]}
